constructor/__init__.py
constructor/condition.py
constructor/main.py
constructor/simulate.py
constructor/substrate.py
constructor/task.py
constructor_lib-0.0.1.dist-info/LICENSE
constructor_lib-0.0.1.dist-info/METADATA
constructor_lib-0.0.1.dist-info/WHEEL
constructor_lib-0.0.1.dist-info/top_level.txt
constructor_lib-0.0.1.dist-info/RECORD
