Metadata-Version: 2.1
Name: constructor-lib
Version: 0.0.1
Summary: Constructor is a Python library that enables the simulation and exploration of physical transformations within the framework of Constructor Theory, focusing on what tasks are possible or impossible under the laws of physics.
Home-page: https://pypi.org/project/constructor-lib/
Author: Chris Mangum
Author-email: csmangum@gmail.com
Classifier: Programming Language :: Python :: 3
Classifier: License :: OSI Approved :: MIT License
Classifier: Operating System :: OS Independent
Requires-Python: >=3.10
License-File: LICENSE
